{
  "background": "#070715",
  "surface": "#0b0824",
  "overlay": "#13122e",
  "base": {
    "100": "#1c1c2c",
    "200": "#484857",
    "300": "#5f5f6d",
    "400": "#777783",
    "500": "#91929b",
    "600": "#ababb2",
    "700": "#c5c5cb",
    "800": "#dfdfe2"
  },
  "blue": {
    "100": "#002031",
    "200": "#004f71",
    "300": "#006791",
    "400": "#0080b2",
    "500": "#009dd6",
    "600": "#00b8f6",
    "700": "#48d5ff",
    "800": "#96edff"
  },
  "green": {
    "100": "#00240a",
    "200": "#005622",
    "300": "#00702f",
    "400": "#008a3d",
    "500": "#00a94e",
    "600": "#00c562",
    "700": "#31e17b",
    "800": "#7df8a4"
  },
  "orange": {
    "100": "#2d1900",
    "200": "#694100",
    "300": "#885500",
    "400": "#a76b00",
    "500": "#c98400",
    "600": "#e89c00",
    "700": "#ffb940",
    "800": "#ffdb93"
  },
  "purple": {
    "100": "#1d1a36",
    "200": "#494279",
    "300": "#60579c",
    "400": "#776dbe",
    "500": "#9287e3",
    "600": "#aba0ff",
    "700": "#c7beff",
    "800": "#e0dcff"
  },
  "red": {
    "100": "#430203",
    "200": "#931315",
    "300": "#b92523",
    "400": "#dc3b36",
    "500": "#fa5e53",
    "600": "#ff8a7e",
    "700": "#ffb3a8",
    "800": "#ffd6cf"
  },
  "teal": {
    "100": "#002220",
    "200": "#00534e",
    "300": "#006c67",
    "400": "#008680",
    "500": "#00a49c",
    "600": "#00bfb6",
    "700": "#0fdcd2",
    "800": "#67f5ec"
  },
  "primary": {
    "100": "#1d1a36",
    "200": "#494279",
    "300": "#60579c",
    "400": "#776dbe",
    "500": "#9287e3",
    "600": "#aba0ff",
    "700": "#c7beff",
    "800": "#e0dcff"
  },
  "secondary": {
    "100": "#002031",
    "200": "#004f71",
    "300": "#006791",
    "400": "#0080b2",
    "500": "#009dd6",
    "600": "#00b8f6",
    "700": "#48d5ff",
    "800": "#96edff"
  }
}